<?xml version="1.0" encoding="windows-1252" ?>
<!DOCTYPE Entity SYSTEM "jbo_03_01.dtd">
<!---->
<Entity
  xmlns="http://xmlns.oracle.com/bc4j"
  Name="Stockmaster"
  Version="11.1.2.62.76"
  DBObjectType="table"
  DBObjectName="STOCKMASTER"
  AliasName="Stockmaster"
  BindingStyle="OracleName"
  UseGlueCode="false">
  <Attribute
    Name="Stockid"
    IsNotNull="true"
    Precision="255"
    ColumnName="STOCKID"
    SQLType="VARCHAR"
    Type="java.lang.String"
    ColumnType="VARCHAR2"
    TableName="STOCKMASTER"
    PrimaryKey="true">
    <DesignTime>
      <Attr Name="_DisplaySize" Value="255"/>
    </DesignTime>
  </Attribute>
  <Attribute
    Name="Categoryid"
    Precision="255"
    ColumnName="CATEGORYID"
    SQLType="VARCHAR"
    Type="java.lang.String"
    ColumnType="VARCHAR2"
    TableName="STOCKMASTER">
    <DesignTime>
      <Attr Name="_DisplaySize" Value="255"/>
    </DesignTime>
  </Attribute>
  <Attribute
    Name="Description"
    Precision="255"
    ColumnName="DESCRIPTION"
    SQLType="VARCHAR"
    Type="java.lang.String"
    ColumnType="VARCHAR2"
    TableName="STOCKMASTER">
    <DesignTime>
      <Attr Name="_DisplaySize" Value="255"/>
    </DesignTime>
  </Attribute>
  <Attribute
    Name="Longdescription"
    Precision="255"
    ColumnName="LONGDESCRIPTION"
    SQLType="VARCHAR"
    Type="java.lang.String"
    ColumnType="VARCHAR2"
    TableName="STOCKMASTER">
    <DesignTime>
      <Attr Name="_DisplaySize" Value="255"/>
    </DesignTime>
  </Attribute>
  <Attribute
    Name="Units"
    Precision="255"
    ColumnName="UNITS"
    SQLType="VARCHAR"
    Type="java.lang.String"
    ColumnType="VARCHAR2"
    TableName="STOCKMASTER">
    <DesignTime>
      <Attr Name="_DisplaySize" Value="255"/>
    </DesignTime>
  </Attribute>
  <Attribute
    Name="Mbflag"
    Precision="255"
    ColumnName="MBFLAG"
    SQLType="VARCHAR"
    Type="java.lang.String"
    ColumnType="VARCHAR2"
    TableName="STOCKMASTER">
    <DesignTime>
      <Attr Name="_DisplaySize" Value="255"/>
    </DesignTime>
  </Attribute>
  <Attribute
    Name="Lastcurcostdate"
    Precision="20"
    ColumnName="LASTCURCOSTDATE"
    SQLType="VARCHAR"
    Type="java.lang.String"
    ColumnType="VARCHAR2"
    TableName="STOCKMASTER">
    <DesignTime>
      <Attr Name="_DisplaySize" Value="20"/>
    </DesignTime>
  </Attribute>
  <Attribute
    Name="Actualcost"
    Precision="20"
    Scale="4"
    ColumnName="ACTUALCOST"
    SQLType="NUMERIC"
    Type="java.math.BigDecimal"
    ColumnType="NUMBER"
    TableName="STOCKMASTER"/>
  <Attribute
    Name="Lastcost"
    Precision="20"
    Scale="4"
    ColumnName="LASTCOST"
    SQLType="NUMERIC"
    Type="java.math.BigDecimal"
    ColumnType="NUMBER"
    TableName="STOCKMASTER"/>
  <Attribute
    Name="Materialcost"
    Precision="20"
    Scale="4"
    ColumnName="MATERIALCOST"
    SQLType="NUMERIC"
    Type="java.math.BigDecimal"
    ColumnType="NUMBER"
    TableName="STOCKMASTER"/>
  <Attribute
    Name="Labourcost"
    Precision="20"
    Scale="4"
    ColumnName="LABOURCOST"
    SQLType="NUMERIC"
    Type="java.math.BigDecimal"
    ColumnType="NUMBER"
    TableName="STOCKMASTER"/>
  <Attribute
    Name="Overheadcost"
    Precision="20"
    Scale="4"
    ColumnName="OVERHEADCOST"
    SQLType="NUMERIC"
    Type="java.math.BigDecimal"
    ColumnType="NUMBER"
    TableName="STOCKMASTER"/>
  <Attribute
    Name="Lowestlevel"
    Precision="8"
    Scale="0"
    ColumnName="LOWESTLEVEL"
    SQLType="NUMERIC"
    Type="java.lang.Integer"
    ColumnType="NUMBER"
    TableName="STOCKMASTER"/>
  <Attribute
    Name="Discontinued"
    Precision="8"
    Scale="0"
    ColumnName="DISCONTINUED"
    SQLType="NUMERIC"
    Type="java.lang.Integer"
    ColumnType="NUMBER"
    TableName="STOCKMASTER"/>
  <Attribute
    Name="Controlled"
    Precision="8"
    Scale="0"
    ColumnName="CONTROLLED"
    SQLType="NUMERIC"
    Type="java.lang.Integer"
    ColumnType="NUMBER"
    TableName="STOCKMASTER"/>
  <Attribute
    Name="Eoq"
    Precision="10"
    Scale="2"
    ColumnName="EOQ"
    SQLType="NUMERIC"
    Type="java.math.BigDecimal"
    ColumnType="NUMBER"
    TableName="STOCKMASTER"/>
  <Attribute
    Name="Volume"
    Precision="20"
    Scale="4"
    ColumnName="VOLUME"
    SQLType="NUMERIC"
    Type="java.math.BigDecimal"
    ColumnType="NUMBER"
    TableName="STOCKMASTER"/>
  <Attribute
    Name="Kgs"
    Precision="20"
    Scale="4"
    ColumnName="KGS"
    SQLType="NUMERIC"
    Type="java.math.BigDecimal"
    ColumnType="NUMBER"
    TableName="STOCKMASTER"/>
  <Attribute
    Name="Barcode"
    Precision="255"
    ColumnName="BARCODE"
    SQLType="VARCHAR"
    Type="java.lang.String"
    ColumnType="VARCHAR2"
    TableName="STOCKMASTER">
    <DesignTime>
      <Attr Name="_DisplaySize" Value="255"/>
    </DesignTime>
  </Attribute>
  <Attribute
    Name="Discountcategory"
    Precision="255"
    ColumnName="DISCOUNTCATEGORY"
    SQLType="VARCHAR"
    Type="java.lang.String"
    ColumnType="VARCHAR2"
    TableName="STOCKMASTER">
    <DesignTime>
      <Attr Name="_DisplaySize" Value="255"/>
    </DesignTime>
  </Attribute>
  <Attribute
    Name="Taxlevel"
    Precision="8"
    Scale="0"
    ColumnName="TAXLEVEL"
    SQLType="NUMERIC"
    Type="java.lang.Integer"
    ColumnType="NUMBER"
    TableName="STOCKMASTER"/>
  <Attribute
    Name="Serialised"
    Precision="8"
    Scale="0"
    ColumnName="SERIALISED"
    SQLType="NUMERIC"
    Type="java.lang.Integer"
    ColumnType="NUMBER"
    TableName="STOCKMASTER"/>
  <Attribute
    Name="Decimalplaces"
    Precision="8"
    Scale="0"
    ColumnName="DECIMALPLACES"
    SQLType="NUMERIC"
    Type="java.lang.Integer"
    ColumnType="NUMBER"
    TableName="STOCKMASTER"/>
  <AccessorAttribute
    Name="Stockcounts"
    Association="project1.Cnt001357Assoc"
    AssociationEnd="project1.Cnt001357Assoc.Stockcounts"
    AssociationOtherEnd="project1.Cnt001357Assoc.Stockmaster"
    Type="oracle.jbo.RowIterator"
    IsUpdateable="false"/>
  <AccessorAttribute
    Name="Recurrsalesorderdetails"
    Association="project1.RecurrorderstkcodeAssoc"
    AssociationEnd="project1.RecurrorderstkcodeAssoc.Recurrsalesorderdetails"
    AssociationOtherEnd="project1.RecurrorderstkcodeAssoc.Stockmaster"
    Type="oracle.jbo.RowIterator"
    IsUpdateable="false"/>
  <AccessorAttribute
    Name="Loctransfers"
    Association="project1.Cnt001310Assoc"
    AssociationEnd="project1.Cnt001310Assoc.Loctransfers"
    AssociationOtherEnd="project1.Cnt001310Assoc.Stockmaster"
    Type="oracle.jbo.RowIterator"
    IsUpdateable="false"/>
  <AccessorAttribute
    Name="Prices"
    Association="project1.Cnt001319Assoc"
    AssociationEnd="project1.Cnt001319Assoc.Prices"
    AssociationOtherEnd="project1.Cnt001319Assoc.Stockmaster"
    Type="oracle.jbo.RowIterator"
    IsUpdateable="false"/>
  <AccessorAttribute
    Name="Locstock"
    Association="project1.Cnt001306Assoc"
    AssociationEnd="project1.Cnt001306Assoc.Locstock"
    AssociationOtherEnd="project1.Cnt001306Assoc.Stockmaster"
    Type="oracle.jbo.RowIterator"
    IsUpdateable="false"/>
  <AccessorAttribute
    Name="Salescatprod"
    Association="project1.J2Assoc"
    AssociationEnd="project1.J2Assoc.Salescatprod"
    AssociationOtherEnd="project1.J2Assoc.Stockmaster"
    Type="oracle.jbo.RowIterator"
    IsUpdateable="false"/>
  <AccessorAttribute
    Name="Salesorderdetails"
    Association="project1.Cnt001338Assoc"
    AssociationEnd="project1.Cnt001338Assoc.Salesorderdetails"
    AssociationOtherEnd="project1.Cnt001338Assoc.Stockmaster"
    Type="oracle.jbo.RowIterator"
    IsUpdateable="false"/>
  <AccessorAttribute
    Name="Contractbom"
    Association="project1.Cnt001259Assoc"
    AssociationEnd="project1.Cnt001259Assoc.Contractbom"
    AssociationOtherEnd="project1.Cnt001259Assoc.Stockmaster"
    Type="oracle.jbo.RowIterator"
    IsUpdateable="false"/>
  <AccessorAttribute
    Name="Stockcheckfreeze"
    Association="project1.Cnt001354Assoc"
    AssociationEnd="project1.Cnt001354Assoc.Stockcheckfreeze"
    AssociationOtherEnd="project1.Cnt001354Assoc.Stockmaster"
    Type="oracle.jbo.server.EntityImpl"
    IsUpdateable="true"/>
  <AccessorAttribute
    Name="Orderdeliverydifferenceslog"
    Association="project1.Cnt001313Assoc"
    AssociationEnd="project1.Cnt001313Assoc.Orderdeliverydifferenceslog"
    AssociationOtherEnd="project1.Cnt001313Assoc.Stockmaster"
    Type="oracle.jbo.RowIterator"
    IsUpdateable="false"/>
  <AccessorAttribute
    Name="Purchdata"
    Association="project1.Cnt001323Assoc"
    AssociationEnd="project1.Cnt001323Assoc.Purchdata"
    AssociationOtherEnd="project1.Cnt001323Assoc.Stockmaster"
    Type="oracle.jbo.RowIterator"
    IsUpdateable="false"/>
  <AccessorAttribute
    Name="Bom"
    Association="project1.Cnt001239Assoc"
    AssociationEnd="project1.Cnt001239Assoc.Bom"
    AssociationOtherEnd="project1.Cnt001239Assoc.Stockmaster"
    Type="oracle.jbo.RowIterator"
    IsUpdateable="false"/>
  <AccessorAttribute
    Name="Bom1"
    Association="project1.Cnt001238Assoc"
    AssociationEnd="project1.Cnt001238Assoc.Bom1"
    AssociationOtherEnd="project1.Cnt001238Assoc.Stockmaster1"
    Type="oracle.jbo.RowIterator"
    IsUpdateable="false"/>
  <AccessorAttribute
    Name="Stockcategory"
    Association="project1.Cnt001360Assoc"
    AssociationEnd="project1.Cnt001360Assoc.Stockcategory"
    AssociationOtherEnd="project1.Cnt001360Assoc.Stockmaster"
    Type="oracle.jbo.server.EntityImpl"
    IsUpdateable="true"/>
  <AccessorAttribute
    Name="Stockmoves"
    Association="project1.Cnt001362Assoc"
    AssociationEnd="project1.Cnt001362Assoc.Stockmoves"
    AssociationOtherEnd="project1.Cnt001362Assoc.Stockmaster"
    Type="oracle.jbo.RowIterator"
    IsUpdateable="false"/>
  <AccessorAttribute
    Name="Stockserialitems"
    Association="project1.Cnt001367Assoc"
    AssociationEnd="project1.Cnt001367Assoc.Stockserialitems"
    AssociationOtherEnd="project1.Cnt001367Assoc.Stockmaster"
    Type="oracle.jbo.RowIterator"
    IsUpdateable="false"/>
  <AccessorAttribute
    Name="Woissues"
    Association="project1.Cnt001393Assoc"
    AssociationEnd="project1.Cnt001393Assoc.Woissues"
    AssociationOtherEnd="project1.Cnt001393Assoc.Stockmaster"
    Type="oracle.jbo.RowIterator"
    IsUpdateable="false"/>
  <AccessorAttribute
    Name="Worequirements"
    Association="project1.Cnt001397Assoc"
    AssociationEnd="project1.Cnt001397Assoc.Worequirements"
    AssociationOtherEnd="project1.Cnt001397Assoc.Stockmaster"
    Type="oracle.jbo.RowIterator"
    IsUpdateable="false"/>
  <AccessorAttribute
    Name="Worksorders"
    Association="project1.Cnt001405Assoc"
    AssociationEnd="project1.Cnt001405Assoc.Worksorders"
    AssociationOtherEnd="project1.Cnt001405Assoc.Stockmaster"
    Type="oracle.jbo.RowIterator"
    IsUpdateable="false"/>
  <Key
    Name="StockmasterPkey"
    PrimaryKey="true">
    <DesignTime>
      <Attr Name="_DBObjectName" Value="STOCKMASTER_PKEY"/>
    </DesignTime>
    <AttrArray Name="Attributes">
      <Item Value="project1.Stockmaster.Stockid"/>
    </AttrArray>
  </Key>
  <Key
    Name="Cnt001360">
    <DesignTime>
      <Attr Name="_referencedKey" Value="STOCKCATEGORY_PKEY"/>
      <Attr Name="_isForeign" Value="true"/>
      <Attr Name="_DBObjectName" Value="CNT001360"/>
    </DesignTime>
    <AttrArray Name="Attributes">
      <Item Value="project1.Stockmaster.Categoryid"/>
    </AttrArray>
  </Key>
</Entity>
